h5visualizer/__init__.py
h5visualizer/__main__.py
h5visualizer-0.0.5.dist-info/LICENSE
h5visualizer-0.0.5.dist-info/METADATA
h5visualizer-0.0.5.dist-info/WHEEL
h5visualizer-0.0.5.dist-info/entry_points.txt
h5visualizer-0.0.5.dist-info/top_level.txt
h5visualizer-0.0.5.dist-info/RECORD
