Metadata-Version: 2.1
Name: h5visualizer
Version: 0.0.5
Summary: A package to visualize h5 models
Author-email: karthikkrazy <goparajukarthik2@gmail.com>
Project-URL: Homepage, https://github.com/krazykarthik2/h5visualizer
Project-URL: Issues, https://github.com/krazykarthik2/h5visualizer/issues
Classifier: Programming Language :: Python :: 3
Classifier: License :: OSI Approved :: MIT License
Classifier: Operating System :: OS Independent
Requires-Python: >=3.8
License-File: LICENSE
Requires-Dist: tensorflow
Requires-Dist: matplotlib
Requires-Dist: numpy
Requires-Dist: argparse
